pixler/__init__.py
pixler-0.1.2.dist-info/WHEEL
pixler-0.1.2.dist-info/METADATA
pixler-0.1.2.dist-info/RECORD
