Metadata-Version: 2.1
Name: pixler
Version: 0.1.2
Summary: Draw a pixel map with braille characters
Home-page: https://github.com/ikornaselur/pixler
License: MIT
Author: Axel
Author-email: pixler@absalon.is
Requires-Python: >=3.6,<4.0
Classifier: License :: OSI Approved :: MIT License
Classifier: Programming Language :: Python :: 3
Classifier: Programming Language :: Python :: 3.6
Classifier: Programming Language :: Python :: 3.7
Classifier: Programming Language :: Python :: 3.8
